rtedbserver/__init__.py
rtedbserver/rteDbServer_s1.ini
rtedbserver/rtedbserver.py
rteDbServer-0.0.1.dist-info/LICENSE
rteDbServer-0.0.1.dist-info/METADATA
rteDbServer-0.0.1.dist-info/WHEEL
rteDbServer-0.0.1.dist-info/top_level.txt
rteDbServer-0.0.1.dist-info/RECORD
