Metadata-Version: 2.1
Name: rteDbServer
Version: 0.0.1
Summary: RTE database server installation
Author: Hendrik du Toit
Author-email: hendrik@brightedge.co.za
Classifier: Development Status :: 1 - Planning
Classifier: Intended Audience :: Developers
Classifier: Topic :: Software Development
Classifier: License :: OSI Approved :: MIT License
Classifier: Programming Language :: Python :: 3.9
License-File: LICENSE
Requires-Dist: beetools
Requires-Dist: configparserext
Requires-Dist: releaselogit
Requires-Dist: semverit
Requires-Dist: termcolor
Requires-Dist: toml
